README.md
setup.py
xdgspec/__init__.py
xdgspec/utils.py
xdgspec/version.py
xdgspec.egg-info/PKG-INFO
xdgspec.egg-info/SOURCES.txt
xdgspec.egg-info/dependency_links.txt
xdgspec.egg-info/top_level.txt