Metadata-Version: 2.1
Name: xdgspec
Version: 0.1.0
Summary: Convenient access to XDG Base Directory Specification variables
Home-page: https://gitlab.com/nobodyinperson/python3-xdgspec
Author: Yann Büchau
Author-email: nobodyinperson@gmx.de
License: GPLv3
Keywords: xdg
Platform: UNKNOWN
Classifier: License :: OSI Approved :: GNU General Public License v3 (GPLv3)
